cvmfsscraper/__init__.py
cvmfsscraper/constants.py
cvmfsscraper/exceptions.py
cvmfsscraper/http_get_models.py
cvmfsscraper/main.py
cvmfsscraper/repository.py
cvmfsscraper/server.py
cvmfsscraper/tests/__init__.py
cvmfsscraper/tests/base.py
cvmfsscraper/tests/data/stratum0.tld/cvmfs/data/.cvmfs_status.json
cvmfsscraper/tests/data/stratum0.tld/cvmfs/data/.cvmfspublished
cvmfsscraper/tests/data/stratum0.tld/cvmfs/info/v1/repositories.json
cvmfsscraper/tests/data/stratum0.tld/cvmfs/test/.cvmfs_status.json
cvmfsscraper/tests/data/stratum0.tld/cvmfs/test/.cvmfspublished
"cvmfsscraper/tests/data/stratum1-au.tld/api/v1.0/geo/x/cvmfs-s1fnal.opensciencegrid.org,cvmfs-stratum-one.cern.ch,cvmfs-stratum-one.ihep.ac.cn"
cvmfsscraper/tests/data/stratum1-au.tld/cvmfs/data/.cvmfs_status.json
cvmfsscraper/tests/data/stratum1-au.tld/cvmfs/data/.cvmfspublished
"cvmfsscraper/tests/data/stratum1-au.tld/cvmfs/data/api/v1.0/geo/x/cvmfs-s1fnal.opensciencegrid.org,cvmfs-stratum-one.cern.ch,cvmfs-stratum-one.ihep.ac.cn"
cvmfsscraper/tests/data/stratum1-au.tld/cvmfs/info/v1/repositories.json
cvmfsscraper/tests/data/stratum1-au.tld/cvmfs/test/.cvmfs_status.json
cvmfsscraper/tests/data/stratum1-au.tld/cvmfs/test/.cvmfspublished
"cvmfsscraper/tests/data/stratum1-au.tld/cvmfs/test/api/v1.0/geo/x/cvmfs-s1fnal.opensciencegrid.org,cvmfs-stratum-one.cern.ch,cvmfs-stratum-one.ihep.ac.cn"
cvmfsscraper/tests/data/stratum1-no.tld/cvmfs/data/.cvmfs_status.json
cvmfsscraper/tests/data/stratum1-no.tld/cvmfs/data/.cvmfspublished
"cvmfsscraper/tests/data/stratum1-no.tld/cvmfs/data/api/v1.0/geo/x/cvmfs-s1fnal.opensciencegrid.org,cvmfs-stratum-one.cern.ch,cvmfs-stratum-one.ihep.ac.cn"
cvmfsscraper/tests/data/stratum1-no.tld/cvmfs/info/v1/repositories.json
cvmfsscraper/tests/data/stratum1-no.tld/cvmfs/test/.cvmfs_status.json
cvmfsscraper/tests/data/stratum1-no.tld/cvmfs/test/.cvmfspublished
cvmfs_server_scraper-0.0.4.dist-info/LICENSE
cvmfs_server_scraper-0.0.4.dist-info/METADATA
cvmfs_server_scraper-0.0.4.dist-info/WHEEL
cvmfs_server_scraper-0.0.4.dist-info/RECORD
