Metadata-Version: 2.1
Name: cvmfs-server-scraper
Version: 0.0.4
Summary: Scrape metadata from CVMFS Stratum servers.
Home-page: https://github.com/eessi/cvmfs-server-scraper
License: GPLv2
Keywords: cvmfs,scrape,eessi
Author: Terje Kvernes
Author-email: terje@kvernes.no
Maintainer: Terje Kvernes
Maintainer-email: terje@kvernes.no
Requires-Python: >=3.8,<4.0
Classifier: Development Status :: 4 - Beta
Classifier: Intended Audience :: Information Technology
Classifier: License :: OSI Approved :: GNU General Public License v2 (GPLv2)
Classifier: License :: Other/Proprietary License
Classifier: Programming Language :: Python
Classifier: Programming Language :: Python :: 3
Classifier: Programming Language :: Python :: 3.8
Classifier: Programming Language :: Python :: 3.9
Classifier: Programming Language :: Python :: 3.10
Classifier: Programming Language :: Python :: 3.11
Classifier: Programming Language :: Python :: 3.12
Classifier: Programming Language :: Python :: 3 :: Only
Classifier: Topic :: Internet :: WWW/HTTP
Requires-Dist: pydantic
Requires-Dist: structlog (>=24,<25)
Project-URL: Documentation, https://github.com/eessi/cvmfs-server-scraper
Project-URL: Repository, https://github.com/eessi/cvmfs-server-scraper
